QQX
