Metadata-Version: 2.1
Name: QQX.py
Version: 108
Summary: supty.py模組
Home-page: UNKNOWN
License: LGPL
Platform: UNKNOWN
